[
   {
      "fields" : {
         "description" : "detects when requests are not handled",
         "name" : "geonode is not working",
         "user_threshold" : {
            "response.time.max_value" : {
               "metric" : "response.time",
               "min" : 500,
               "max" : null,
               "description" : "Response time is higher than",
               "steps" : null
            },
            "request.count.max_timeout" : {
               "min" : 60,
               "metric" : "request.count",
               "max" : null,
               "description" : "No response for at least",
               "steps" : null
            },
            "request.count.min_value" : {
               "metric" : "request.count",
               "min" : 0,
               "description" : "Number of handled requests is lower than",
               "max" : 10,
               "steps" : 3
            }
         },
         "active" : true,
         "grace_period" : "00:10:00",
         "last_send" : "2017-08-29T17:37:41",
         "severity" : "error"
      },
      "pk" : 2,
      "model" : "monitoring.notificationcheck"
   },
   {
      "pk" : 3,
      "fields" : {
         "field_option" : "min_value",
         "steps" : 3,
         "min_value" : "0.0000",
         "description" : "Number of handled requests is lower than",
         "max_value" : "10.0000",
         "use_event_type" : false,
         "notification_check" : 2,
         "metric" : 2,
         "use_service" : false,
         "use_resource" : false,
         "use_label" : false
      },
      "model" : "monitoring.notificationmetricdefinition"
   },
   {
      "model" : "monitoring.notificationmetricdefinition",
      "fields" : {
         "max_value" : null,
         "use_event_type" : false,
         "use_service" : false,
         "use_resource" : false,
         "notification_check" : 2,
         "metric" : 2,
         "use_label" : false,
         "steps" : null,
         "field_option" : "max_timeout",
         "min_value" : "60.0000",
         "description" : "No response for at least"
      },
      "pk" : 4
   },
   {
      "fields" : {
         "notification_check" : 2,
         "metric" : 11,
         "use_resource" : false,
         "use_service" : false,
         "use_label" : false,
         "max_value" : null,
         "use_event_type" : false,
         "min_value" : "500.0000",
         "description" : "Response time is higher than",
         "steps" : null,
         "field_option" : "max_value"
      },
      "pk" : 5,
      "model" : "monitoring.notificationmetricdefinition"
   },
   {
      "pk" : 20,
      "fields" : {
         "event_type" : null,
         "active" : true,
         "notification_check" : 2,
         "metric" : 2,
         "max_value" : null,
         "service" : null,
         "label" : null,
         "min_value" : null,
         "max_timeout" : "00:02:00",
         "definition" : 4,
         "resource" : null
      },
      "model" : "monitoring.metricnotificationcheck"
   },
   {
      "fields" : {
         "min_value" : "10.0000",
         "max_timeout" : null,
         "resource" : null,
         "definition" : 3,
         "active" : true,
         "event_type" : null,
         "metric" : 2,
         "notification_check" : 2,
         "label" : null,
         "max_value" : null,
         "service" : null
      },
      "pk" : 21,
      "model" : "monitoring.metricnotificationcheck"
   },
   {
      "model" : "monitoring.metricnotificationcheck",
      "pk" : 22,
      "fields" : {
         "resource" : null,
         "definition" : 5,
         "min_value" : null,
         "max_timeout" : null,
         "label" : null,
         "max_value" : null,
         "service" : null,
         "active" : true,
         "event_type" : null,
         "metric" : 11,
         "notification_check" : 2
      }
   }
]
