<?xml version="1.0"  encoding="ISO-8859-1"?>

 <Configure class="org.eclipse.jetty.webapp.WebAppContext">
     <Set name="contextPath">/geoserver</Set>
     <Set name="war"><SystemProperty name="jetty.home" default="../geoserver"/></Set>
     <Set name="descriptor">/WEB-INF/web.xml</Set>
     <Set name="parentLoaderPriority">false</Set>
     <Call name="setAttribute">
       <Arg>org.eclipse.jetty.server.webapp.WebInfIncludeJarPattern</Arg>
       <Arg>WONTMATCH</Arg>
     </Call>
  </Configure>
